onlyaff/__init__.py
onlyaff/api/__init__.py
onlyaff/api/core.py
onlyaff/api/di.py
onlyaff/api/main.py
onlyaff/api/schemas.py
onlyaff/clerk/__init__.py
onlyaff/clerk/provider.py
onlyaff/clerk/service.py
onlyaff/config/__init__.py
onlyaff/config/provider.py
onlyaff/config/settings.py
onlyaff/health/__init__.py
onlyaff/health/api.py
onlyaff/health/schemas.py
onlyaff/util/__init__.py
onlyaff/util/typing.py
onlyaff-0.1.0.dist-info/METADATA
onlyaff-0.1.0.dist-info/WHEEL
onlyaff-0.1.0.dist-info/RECORD
