Metadata-Version: 2.1
Name: onlyaff
Version: 0.1.0
Summary: 
Author: Công Trần
Author-email: trancong12102@gmail.com
Requires-Python: >=3.12,<4.0
Classifier: Programming Language :: Python :: 3
Classifier: Programming Language :: Python :: 3.12
Requires-Dist: clerk-backend-sdk (>=1.0.0,<2.0.0)
Requires-Dist: dishka (>=1.3.0,<2.0.0)
Requires-Dist: fastapi[standard] (>=0.112.2,<0.113.0)
Requires-Dist: pydantic (>=2.8.2,<3.0.0)
Requires-Dist: pydantic-settings (>=2.4.0,<3.0.0)
Requires-Dist: weebuild-clerk-backend-api-client (>=1.0.0,<2.0.0)
